h5grove/__init__.py
h5grove/content.py
h5grove/encoders.py
h5grove/fastapi_utils.py
h5grove/flask_utils.py
h5grove/models.py
h5grove/tornado_utils.py
h5grove/utils.py
h5grove-2.3.0.dist-info/LICENSE
h5grove-2.3.0.dist-info/METADATA
h5grove-2.3.0.dist-info/WHEEL
h5grove-2.3.0.dist-info/top_level.txt
h5grove-2.3.0.dist-info/RECORD
