Metadata-Version: 2.1
Name: h5grove
Version: 2.3.0
Summary: Core utilities to serve HDF5 file contents
Home-page: https://github.com/silx-kit/h5grove
Author: European Synchrotron Radiation Facility
Author-email: h5web@esrf.fr
License: MIT
Project-URL: Bug Tracker, https://github.com/silx-kit/h5grove/-/issues
Classifier: License :: OSI Approved :: MIT License
Classifier: Programming Language :: Python :: 3
Requires-Python: >=3.8
License-File: LICENSE
Requires-Dist: numpy
Requires-Dist: orjson
Requires-Dist: h5py>=3
Requires-Dist: tifffile
Requires-Dist: typing-extensions
Provides-Extra: fastapi
Requires-Dist: fastapi; extra == "fastapi"
Requires-Dist: pydantic>2; extra == "fastapi"
Requires-Dist: pydantic-settings; extra == "fastapi"
Requires-Dist: uvicorn; extra == "fastapi"
Provides-Extra: flask
Requires-Dist: Flask; extra == "flask"
Requires-Dist: Flask-Compress; extra == "flask"
Requires-Dist: Flask-Cors; extra == "flask"
Provides-Extra: tornado
Requires-Dist: tornado; extra == "tornado"
Provides-Extra: dev
Requires-Dist: black; extra == "dev"
Requires-Dist: bump2version; extra == "dev"
Requires-Dist: check-manifest; extra == "dev"
Requires-Dist: eval_type_backport; extra == "dev"
Requires-Dist: flake8; extra == "dev"
Requires-Dist: h5grove[fastapi]; extra == "dev"
Requires-Dist: h5grove[flask]; extra == "dev"
Requires-Dist: h5grove[tornado]; extra == "dev"
Requires-Dist: invoke; extra == "dev"
Requires-Dist: mypy; extra == "dev"
Requires-Dist: myst-parser; extra == "dev"
Requires-Dist: httpx>=0.23; extra == "dev"
Requires-Dist: pytest; extra == "dev"
Requires-Dist: pytest-benchmark; extra == "dev"
Requires-Dist: pytest-cov; extra == "dev"
Requires-Dist: pytest-tornado; extra == "dev"
Requires-Dist: sphinx; extra == "dev"
Requires-Dist: sphinx-argparse; extra == "dev"
Requires-Dist: sphinx-autobuild; extra == "dev"
Requires-Dist: h5grove[tornado]; extra == "dev"
Requires-Dist: types-contextvars; extra == "dev"
Requires-Dist: types-dataclasses; extra == "dev"
Requires-Dist: types-orjson; extra == "dev"
Requires-Dist: types-setuptools; extra == "dev"
